{
    "_comment": "Maps alternate team names (from ESPN, Yahoo, KenPom, Vegas, NCAA, CBS) to Bart Torvik canonical names. Keys are aliases, values are the Torvik name.",

    "UConn": "Connecticut",
    "UCONN": "Connecticut",
    "Conn": "Connecticut",
    "Connecticut Huskies": "Connecticut",
    "UConn Huskies": "Connecticut",

    "UNC": "North Carolina",
    "North Carolina Tar Heels": "North Carolina",
    "N Carolina": "North Carolina",
    "N. Carolina": "North Carolina",
    "NC": "North Carolina",

    "NC State": "N.C. State",
    "North Carolina State": "N.C. State",
    "North Carolina St.": "N.C. State",
    "North Carolina St": "N.C. State",
    "NC St": "N.C. State",
    "NC St.": "N.C. State",
    "NCSU": "N.C. State",
    "N.C. State Wolfpack": "N.C. State",
    "NC State Wolfpack": "N.C. State",

    "Southern California": "USC",
    "Southern Cal": "USC",
    "So. California": "USC",
    "S California": "USC",
    "Southern California Trojans": "USC",
    "USC Trojans": "USC",

    "Ole Miss": "Mississippi",
    "Ole Miss Rebels": "Mississippi",
    "Mississippi Rebels": "Mississippi",
    "Miss": "Mississippi",

    "Miss State": "Mississippi St.",
    "Miss St": "Mississippi St.",
    "Miss. State": "Mississippi St.",
    "Miss. St.": "Mississippi St.",
    "Mississippi State": "Mississippi St.",
    "Mississippi St": "Mississippi St.",
    "MSU": "Mississippi St.",
    "Mississippi State Bulldogs": "Mississippi St.",

    "Pitt": "Pittsburgh",
    "Pitt Panthers": "Pittsburgh",
    "Pittsburgh Panthers": "Pittsburgh",

    "St. John's": "St. John's",
    "Saint John's": "St. John's",
    "St John's": "St. John's",
    "St. Johns": "St. John's",
    "Saint Johns": "St. John's",
    "St Johns": "St. John's",
    "St. John's Red Storm": "St. John's",
    "Saint John's Red Storm": "St. John's",

    "Saint Mary's (CA)": "Saint Mary's",
    "St. Mary's": "Saint Mary's",
    "St Mary's": "Saint Mary's",
    "St. Marys": "Saint Mary's",
    "Saint Marys": "Saint Mary's",
    "St Marys": "Saint Mary's",
    "Saint Mary's Gaels": "Saint Mary's",
    "St. Mary's (CA)": "Saint Mary's",

    "Saint Peter's": "Saint Peter's",
    "St. Peter's": "Saint Peter's",
    "St Peter's": "Saint Peter's",
    "St. Peters": "Saint Peter's",
    "Saint Peters": "Saint Peter's",
    "St Peters": "Saint Peter's",
    "Saint Peter's Peacocks": "Saint Peter's",

    "Saint Joseph's": "Saint Joseph's",
    "St. Joseph's": "Saint Joseph's",
    "St Joseph's": "Saint Joseph's",
    "St. Josephs": "Saint Joseph's",
    "Saint Josephs": "Saint Joseph's",
    "St Josephs": "Saint Joseph's",
    "Saint Joseph's Hawks": "Saint Joseph's",

    "Saint Louis": "Saint Louis",
    "St. Louis": "Saint Louis",
    "St Louis": "Saint Louis",
    "Saint Louis Billikens": "Saint Louis",
    "SLU": "Saint Louis",

    "Saint Francis": "Saint Francis",
    "St. Francis (PA)": "Saint Francis",
    "St. Francis PA": "Saint Francis",
    "St Francis": "Saint Francis",
    "Saint Francis (PA)": "Saint Francis",
    "St. Francis": "Saint Francis",

    "St. Bonaventure": "St. Bonaventure",
    "Saint Bonaventure": "St. Bonaventure",
    "St Bonaventure": "St. Bonaventure",
    "St. Bonaventure Bonnies": "St. Bonaventure",
    "Bonnies": "St. Bonaventure",

    "St. Thomas": "St. Thomas",
    "Saint Thomas": "St. Thomas",
    "St Thomas": "St. Thomas",
    "St. Thomas (MN)": "St. Thomas",
    "Saint Thomas (MN)": "St. Thomas",

    "Mount St. Mary's": "Mount St. Mary's",
    "Mt. St. Mary's": "Mount St. Mary's",
    "Mount St Marys": "Mount St. Mary's",
    "Mt St Marys": "Mount St. Mary's",
    "Mount Saint Mary's": "Mount St. Mary's",
    "Mt. Saint Mary's": "Mount St. Mary's",
    "Mount St. Marys": "Mount St. Mary's",

    "Loyola-Chicago": "Loyola Chicago",
    "Loyola (IL)": "Loyola Chicago",
    "Loyola IL": "Loyola Chicago",
    "Loyola Chi": "Loyola Chicago",
    "Loyola Ramblers": "Loyola Chicago",
    "Loyola Chicago Ramblers": "Loyola Chicago",

    "Loyola (MD)": "Loyola MD",
    "Loyola Maryland": "Loyola MD",
    "Loyola-Maryland": "Loyola MD",

    "Iowa State": "Iowa St.",
    "Iowa St": "Iowa St.",
    "Iowa State Cyclones": "Iowa St.",
    "ISU": "Iowa St.",

    "Ohio State": "Ohio St.",
    "Ohio St": "Ohio St.",
    "Ohio State Buckeyes": "Ohio St.",
    "OSU": "Ohio St.",

    "Michigan State": "Michigan St.",
    "Michigan St": "Michigan St.",
    "Mich State": "Michigan St.",
    "Mich St": "Michigan St.",
    "Mich. State": "Michigan St.",
    "Mich. St.": "Michigan St.",
    "Michigan State Spartans": "Michigan St.",

    "Oklahoma State": "Oklahoma St.",
    "Oklahoma St": "Oklahoma St.",
    "Okla State": "Oklahoma St.",
    "Okla St": "Oklahoma St.",
    "Okla. State": "Oklahoma St.",
    "Okla. St.": "Oklahoma St.",
    "Oklahoma State Cowboys": "Oklahoma St.",

    "Kansas State": "Kansas St.",
    "Kansas St": "Kansas St.",
    "K-State": "Kansas St.",
    "KSU": "Kansas St.",
    "Kansas State Wildcats": "Kansas St.",

    "Penn State": "Penn St.",
    "Penn St": "Penn St.",
    "Penn State Nittany Lions": "Penn St.",
    "PSU": "Penn St.",

    "Arizona State": "Arizona St.",
    "Arizona St": "Arizona St.",
    "Ariz State": "Arizona St.",
    "Ariz St": "Arizona St.",
    "Ariz. State": "Arizona St.",
    "Ariz. St.": "Arizona St.",
    "ASU": "Arizona St.",
    "Arizona State Sun Devils": "Arizona St.",

    "Oregon State": "Oregon St.",
    "Oregon St": "Oregon St.",
    "Oregon State Beavers": "Oregon St.",

    "Washington State": "Washington St.",
    "Washington St": "Washington St.",
    "Wash State": "Washington St.",
    "Wash St": "Washington St.",
    "Wazzu": "Washington St.",
    "Washington State Cougars": "Washington St.",

    "Florida State": "Florida St.",
    "Florida St": "Florida St.",
    "Fla State": "Florida St.",
    "Fla St": "Florida St.",
    "Fla. State": "Florida St.",
    "Fla. St.": "Florida St.",
    "FSU": "Florida St.",
    "Florida State Seminoles": "Florida St.",

    "Boise State": "Boise St.",
    "Boise St": "Boise St.",
    "Boise State Broncos": "Boise St.",

    "Colorado State": "Colorado St.",
    "Colorado St": "Colorado St.",
    "Colo State": "Colorado St.",
    "Colo St": "Colorado St.",
    "Colo. State": "Colorado St.",
    "Colo. St.": "Colorado St.",
    "CSU": "Colorado St.",
    "Colorado State Rams": "Colorado St.",

    "Fresno State": "Fresno St.",
    "Fresno St": "Fresno St.",
    "Fresno State Bulldogs": "Fresno St.",

    "San Diego State": "San Diego St.",
    "San Diego St": "San Diego St.",
    "SDSU": "San Diego St.",
    "San Diego State Aztecs": "San Diego St.",

    "San Jose State": "San Jose St.",
    "San Jose St": "San Jose St.",
    "SJSU": "San Jose St.",
    "San Jose State Spartans": "San Jose St.",

    "Utah State": "Utah St.",
    "Utah St": "Utah St.",
    "USU": "Utah St.",
    "Utah State Aggies": "Utah St.",

    "Wichita State": "Wichita St.",
    "Wichita St": "Wichita St.",
    "Wichita State Shockers": "Wichita St.",

    "Illinois State": "Illinois St.",
    "Illinois St": "Illinois St.",
    "Illinois State Redbirds": "Illinois St.",

    "Indiana State": "Indiana St.",
    "Indiana St": "Indiana St.",
    "Indiana State Sycamores": "Indiana St.",

    "Missouri State": "Missouri St.",
    "Missouri St": "Missouri St.",
    "Missouri State Bears": "Missouri St.",

    "Ball State": "Ball St.",
    "Ball St": "Ball St.",
    "Ball State Cardinals": "Ball St.",

    "Kent State": "Kent St.",
    "Kent St": "Kent St.",
    "Kent State Golden Flashes": "Kent St.",

    "Appalachian State": "Appalachian St.",
    "Appalachian St": "Appalachian St.",
    "App State": "Appalachian St.",
    "App St": "Appalachian St.",
    "Appalachian State Mountaineers": "Appalachian St.",

    "Georgia State": "Georgia St.",
    "Georgia St": "Georgia St.",
    "Georgia State Panthers": "Georgia St.",

    "Alabama State": "Alabama St.",
    "Alabama St": "Alabama St.",
    "Alabama State Hornets": "Alabama St.",

    "Alcorn State": "Alcorn St.",
    "Alcorn St": "Alcorn St.",
    "Alcorn State Braves": "Alcorn St.",

    "Coppin State": "Coppin St.",
    "Coppin St": "Coppin St.",
    "Coppin State Eagles": "Coppin St.",

    "Delaware State": "Delaware St.",
    "Delaware St": "Delaware St.",
    "Delaware State Hornets": "Delaware St.",

    "Grambling State": "Grambling St.",
    "Grambling St": "Grambling St.",
    "Grambling": "Grambling St.",
    "Grambling State Tigers": "Grambling St.",

    "Jackson State": "Jackson St.",
    "Jackson St": "Jackson St.",
    "Jackson State Tigers": "Jackson St.",

    "Jacksonville State": "Jacksonville St.",
    "Jacksonville St": "Jacksonville St.",
    "Jax State": "Jacksonville St.",
    "Jacksonville State Gamecocks": "Jacksonville St.",

    "Kennesaw State": "Kennesaw St.",
    "Kennesaw St": "Kennesaw St.",
    "Kennesaw State Owls": "Kennesaw St.",
    "KSU Owls": "Kennesaw St.",

    "McNeese State": "McNeese St.",
    "McNeese St": "McNeese St.",
    "McNeese": "McNeese St.",
    "McNeese State Cowboys": "McNeese St.",

    "Mississippi Valley State": "Mississippi Valley St.",
    "Mississippi Valley St": "Mississippi Valley St.",
    "MVSU": "Mississippi Valley St.",
    "Miss Valley St": "Mississippi Valley St.",
    "Miss. Valley St.": "Mississippi Valley St.",

    "Montana State": "Montana St.",
    "Montana St": "Montana St.",
    "Montana State Bobcats": "Montana St.",

    "Morehead State": "Morehead St.",
    "Morehead St": "Morehead St.",
    "Morehead State Eagles": "Morehead St.",

    "Morgan State": "Morgan St.",
    "Morgan St": "Morgan St.",
    "Morgan State Bears": "Morgan St.",

    "Murray State": "Murray St.",
    "Murray St": "Murray St.",
    "Murray State Racers": "Murray St.",

    "New Mexico State": "New Mexico St.",
    "New Mexico St": "New Mexico St.",
    "NM State": "New Mexico St.",
    "NMSU": "New Mexico St.",
    "New Mexico State Aggies": "New Mexico St.",

    "Nicholls State": "Nicholls St.",
    "Nicholls St": "Nicholls St.",
    "Nicholls": "Nicholls St.",
    "Nicholls State Colonels": "Nicholls St.",

    "Norfolk State": "Norfolk St.",
    "Norfolk St": "Norfolk St.",
    "Norfolk State Spartans": "Norfolk St.",

    "North Dakota State": "North Dakota St.",
    "North Dakota St": "North Dakota St.",
    "NDSU": "North Dakota St.",
    "North Dakota State Bison": "North Dakota St.",

    "Northwestern State": "Northwestern St.",
    "Northwestern St": "Northwestern St.",
    "Northwestern State Demons": "Northwestern St.",

    "Portland State": "Portland St.",
    "Portland St": "Portland St.",
    "Portland State Vikings": "Portland St.",

    "Sacramento State": "Sacramento St.",
    "Sacramento St": "Sacramento St.",
    "Sac State": "Sacramento St.",
    "Sacramento State Hornets": "Sacramento St.",

    "South Carolina State": "South Carolina St.",
    "South Carolina St": "South Carolina St.",
    "SC State": "South Carolina St.",
    "South Carolina State Bulldogs": "South Carolina St.",

    "South Dakota State": "South Dakota St.",
    "South Dakota St": "South Dakota St.",
    "SDSU Jackrabbits": "South Dakota St.",
    "South Dakota State Jackrabbits": "South Dakota St.",

    "Southeast Missouri State": "Southeast Missouri St.",
    "Southeast Missouri St": "Southeast Missouri St.",
    "SE Missouri State": "Southeast Missouri St.",
    "SE Missouri St": "Southeast Missouri St.",
    "SE Missouri St.": "Southeast Missouri St.",
    "SEMO": "Southeast Missouri St.",

    "Tennessee State": "Tennessee St.",
    "Tennessee St": "Tennessee St.",
    "Tennessee State Tigers": "Tennessee St.",

    "Texas State": "Texas St.",
    "Texas St": "Texas St.",
    "Texas State Bobcats": "Texas St.",
    "TXST": "Texas St.",

    "Weber State": "Weber St.",
    "Weber St": "Weber St.",
    "Weber State Wildcats": "Weber St.",

    "Wright State": "Wright St.",
    "Wright St": "Wright St.",
    "Wright State Raiders": "Wright St.",

    "Youngstown State": "Youngstown St.",
    "Youngstown St": "Youngstown St.",
    "Youngstown State Penguins": "Youngstown St.",

    "Idaho State": "Idaho St.",
    "Idaho St": "Idaho St.",
    "Idaho State Bengals": "Idaho St.",

    "Sam Houston State": "Sam Houston St.",
    "Sam Houston St": "Sam Houston St.",
    "Sam Houston": "Sam Houston St.",
    "SHSU": "Sam Houston St.",
    "Sam Houston State Bearkats": "Sam Houston St.",

    "Tarleton State": "Tarleton St.",
    "Tarleton St": "Tarleton St.",
    "Tarleton": "Tarleton St.",
    "Tarleton State Texans": "Tarleton St.",

    "Cleveland State": "Cleveland St.",
    "Cleveland St": "Cleveland St.",
    "Cleveland State Vikings": "Cleveland St.",

    "Long Beach State": "Long Beach St.",
    "Long Beach St": "Long Beach St.",
    "LBSU": "Long Beach St.",
    "Long Beach State 49ers": "Long Beach St.",
    "Long Beach St. 49ers": "Long Beach St.",

    "Chicago State": "Chicago St.",
    "Chicago St": "Chicago St.",
    "Chicago State Cougars": "Chicago St.",

    "Arkansas State": "Arkansas St.",
    "Arkansas St": "Arkansas St.",
    "Arkansas State Red Wolves": "Arkansas St.",

    "East Tennessee State": "East Tennessee St.",
    "East Tennessee St": "East Tennessee St.",
    "ETSU": "East Tennessee St.",
    "East Tennessee State Buccaneers": "East Tennessee St.",

    "Cal State Bakersfield": "Cal St. Bakersfield",
    "Cal St Bakersfield": "Cal St. Bakersfield",
    "Cal State-Bakersfield": "Cal St. Bakersfield",
    "CSU Bakersfield": "Cal St. Bakersfield",
    "CSUB": "Cal St. Bakersfield",
    "Cal St. Bakersfield Roadrunners": "Cal St. Bakersfield",

    "Cal State Fullerton": "Cal St. Fullerton",
    "Cal St Fullerton": "Cal St. Fullerton",
    "Cal State-Fullerton": "Cal St. Fullerton",
    "CSU Fullerton": "Cal St. Fullerton",
    "CSUF": "Cal St. Fullerton",
    "Cal St. Fullerton Titans": "Cal St. Fullerton",

    "Cal State Northridge": "Cal St. Northridge",
    "Cal St Northridge": "Cal St. Northridge",
    "Cal State-Northridge": "Cal St. Northridge",
    "CSU Northridge": "Cal St. Northridge",
    "CSUN": "Cal St. Northridge",
    "Cal St. Northridge Matadors": "Cal St. Northridge",

    "Texas-El Paso": "UTEP",
    "Texas El Paso": "UTEP",
    "UT-El Paso": "UTEP",
    "UT El Paso": "UTEP",
    "Texas-EP": "UTEP",
    "UTEP Miners": "UTEP",

    "Texas-San Antonio": "UTSA",
    "Texas San Antonio": "UTSA",
    "UT San Antonio": "UTSA",
    "UT-San Antonio": "UTSA",
    "UTSA Roadrunners": "UTSA",

    "Texas-Arlington": "UT Arlington",
    "Texas Arlington": "UT Arlington",
    "UT-Arlington": "UT Arlington",
    "UTA": "UT Arlington",
    "UT Arlington Mavericks": "UT Arlington",

    "UT-Rio Grande Valley": "UT Rio Grande Valley",
    "Texas Rio Grande Valley": "UT Rio Grande Valley",
    "Texas-Rio Grande Valley": "UT Rio Grande Valley",
    "UTRGV": "UT Rio Grande Valley",
    "UT Rio Grande Valley Vaqueros": "UT Rio Grande Valley",

    "Nevada-Las Vegas": "UNLV",
    "Nevada Las Vegas": "UNLV",
    "UNLV Rebels": "UNLV",
    "UNLV Runnin' Rebels": "UNLV",

    "Virginia Commonwealth": "VCU",
    "Virginia Commonwealth Rams": "VCU",
    "VCU Rams": "VCU",

    "Central Florida": "UCF",
    "Central Florida Knights": "UCF",
    "UCF Knights": "UCF",

    "Alabama-Birmingham": "UAB",
    "Alabama Birmingham": "UAB",
    "Alabama at Birmingham": "UAB",
    "UAB Blazers": "UAB",

    "Southern Methodist": "SMU",
    "Southern Methodist Mustangs": "SMU",
    "SMU Mustangs": "SMU",

    "Texas Christian": "TCU",
    "Texas Christian Horned Frogs": "TCU",
    "TCU Horned Frogs": "TCU",

    "Brigham Young": "BYU",
    "Brigham Young Cougars": "BYU",
    "BYU Cougars": "BYU",

    "Louisiana State": "LSU",
    "Louisiana State Tigers": "LSU",
    "LSU Tigers": "LSU",

    "Florida International": "FIU",
    "Florida Intl": "FIU",
    "Florida International Panthers": "FIU",
    "FIU Panthers": "FIU",

    "SIU-Edwardsville": "SIU Edwardsville",
    "Southern Illinois-Edwardsville": "SIU Edwardsville",
    "Southern Illinois Edwardsville": "SIU Edwardsville",
    "SIUE": "SIU Edwardsville",
    "SIU-E": "SIU Edwardsville",
    "SIU Edwardsville Cougars": "SIU Edwardsville",

    "Illinois-Chicago": "Illinois Chicago",
    "Illinois Chicago Flames": "Illinois Chicago",
    "UIC": "Illinois Chicago",

    "Maryland-Baltimore County": "UMBC",
    "Maryland Baltimore County": "UMBC",
    "UMBC Retrievers": "UMBC",

    "Missouri-Kansas City": "UMKC",
    "Missouri Kansas City": "UMKC",
    "UMKC Kangaroos": "UMKC",

    "Massachusetts-Lowell": "UMass Lowell",
    "Massachusetts Lowell": "UMass Lowell",
    "UMass-Lowell": "UMass Lowell",

    "Massachusetts": "Massachusetts",
    "UMass": "Massachusetts",
    "UMass Minutemen": "Massachusetts",

    "UNC-Asheville": "UNC Asheville",
    "UNC Asheville Bulldogs": "UNC Asheville",
    "North Carolina-Asheville": "UNC Asheville",

    "UNC-Greensboro": "UNC Greensboro",
    "UNC Greensboro Spartans": "UNC Greensboro",
    "North Carolina-Greensboro": "UNC Greensboro",
    "UNCG": "UNC Greensboro",

    "UNC-Wilmington": "UNC Wilmington",
    "UNC Wilmington Seahawks": "UNC Wilmington",
    "North Carolina-Wilmington": "UNC Wilmington",
    "UNCW": "UNC Wilmington",

    "USC-Upstate": "USC Upstate",
    "South Carolina Upstate": "USC Upstate",
    "South Carolina-Upstate": "USC Upstate",
    "USC Upstate Spartans": "USC Upstate",

    "Long Island": "LIU",
    "Long Island University": "LIU",
    "LIU Sharks": "LIU",

    "New Jersey Tech": "NJIT",
    "New Jersey Inst. of Technology": "NJIT",
    "NJIT Highlanders": "NJIT",
    "NJ Tech": "NJIT",

    "Nebraska-Omaha": "Nebraska Omaha",
    "Nebraska Omaha Mavericks": "Nebraska Omaha",
    "UNO": "Nebraska Omaha",
    "Omaha": "Nebraska Omaha",
    "Omaha Mavericks": "Nebraska Omaha",

    "Texas A&M-Corpus Christi": "Texas A&M Corpus Chris",
    "Texas A&M Corpus Christi": "Texas A&M Corpus Chris",
    "Texas A&M-CC": "Texas A&M Corpus Chris",
    "Texas A&M CC": "Texas A&M Corpus Chris",
    "A&M-Corpus Christi": "Texas A&M Corpus Chris",
    "TAMUCC": "Texas A&M Corpus Chris",

    "Texas A&M Aggies": "Texas A&M",
    "Texas A&M University": "Texas A&M",
    "TAMU": "Texas A&M",

    "East Texas A&M Lions": "East Texas A&M",
    "Texas A&M-Commerce": "East Texas A&M",
    "Texas A&M Commerce": "East Texas A&M",
    "ETAMU": "East Texas A&M",
    "A&M-Commerce": "East Texas A&M",

    "Arkansas-Pine Bluff": "Arkansas Pine Bluff",
    "Arkansas Pine Bluff Golden Lions": "Arkansas Pine Bluff",
    "Ark Pine Bluff": "Arkansas Pine Bluff",
    "Ark-Pine Bluff": "Arkansas Pine Bluff",
    "UAPB": "Arkansas Pine Bluff",

    "North Carolina A&T": "North Carolina A&T",
    "NC A&T": "North Carolina A&T",
    "North Carolina A&T Aggies": "North Carolina A&T",
    "N.C. A&T": "North Carolina A&T",

    "North Carolina Central": "North Carolina Central",
    "NC Central": "North Carolina Central",
    "NCCU": "North Carolina Central",
    "N.C. Central": "North Carolina Central",

    "Maryland-Eastern Shore": "Maryland Eastern Shore",
    "Maryland East. Shore": "Maryland Eastern Shore",
    "MD Eastern Shore": "Maryland Eastern Shore",
    "UMES": "Maryland Eastern Shore",

    "Central Connecticut State": "Central Connecticut",
    "Central Conn": "Central Connecticut",
    "Central Conn St": "Central Connecticut",
    "Central Conn. St.": "Central Connecticut",
    "Central Connecticut St.": "Central Connecticut",
    "CCSU": "Central Connecticut",

    "Prairie View": "Prairie View A&M",
    "Prairie View A&M Panthers": "Prairie View A&M",
    "PVAMU": "Prairie View A&M",

    "Tennessee-Martin": "Tennessee Martin",
    "Tennessee Martin Skyhawks": "Tennessee Martin",
    "UT Martin": "Tennessee Martin",
    "UT-Martin": "Tennessee Martin",
    "UTM": "Tennessee Martin",

    "Southeast Louisiana": "Southeastern Louisiana",
    "SE Louisiana": "Southeastern Louisiana",
    "Southeastern La.": "Southeastern Louisiana",

    "Southern Miss": "Southern Miss",
    "Southern Mississippi": "Southern Miss",
    "So. Miss": "Southern Miss",
    "USM": "Southern Miss",
    "Southern Miss Golden Eagles": "Southern Miss",

    "Texas Southern": "Texas Southern",
    "Texas Southern Tigers": "Texas Southern",
    "TSU": "Texas Southern",
    "TXSO": "Texas Southern",

    "Stephen F. Austin": "Stephen F. Austin",
    "SFA": "Stephen F. Austin",
    "Stephen F Austin": "Stephen F. Austin",
    "SF Austin": "Stephen F. Austin",

    "Abilene Christian": "Abilene Christian",
    "Abil Christian": "Abilene Christian",
    "ACU": "Abilene Christian",
    "Abilene Christian Wildcats": "Abilene Christian",

    "Miami (FL)": "Miami FL",
    "Miami (Fla.)": "Miami FL",
    "Miami Florida": "Miami FL",
    "Miami Hurricanes": "Miami FL",
    "Miami (FL) Hurricanes": "Miami FL",

    "Miami (OH)": "Miami OH",
    "Miami (Ohio)": "Miami OH",
    "Miami Ohio": "Miami OH",
    "Miami RedHawks": "Miami OH",
    "Miami (OH) RedHawks": "Miami OH",

    "DePaul Blue Demons": "DePaul",

    "Southeastern La": "Southeastern Louisiana",
    "Southeastern Louisiana Lions": "Southeastern Louisiana",

    "Incarnate Word Cardinals": "Incarnate Word",
    "UIW": "Incarnate Word",

    "Cal Baptist": "Cal Baptist",
    "California Baptist": "Cal Baptist",
    "CBU": "Cal Baptist",
    "Cal Baptist Lancers": "Cal Baptist",

    "Charleston Southern Buccaneers": "Charleston Southern",
    "Chas Southern": "Charleston Southern",

    "IU Indianapolis": "IU Indy",
    "IUPUI": "IU Indy",
    "Indiana University Indianapolis": "IU Indy",
    "IU-Indianapolis": "IU Indy",

    "South Florida Bulls": "South Florida",
    "USF": "South Florida",

    "North Texas Mean Green": "North Texas",
    "UNT": "North Texas",

    "North Florida Ospreys": "North Florida",
    "UNF": "North Florida",

    "Boston College Eagles": "Boston College",
    "BC": "Boston College",

    "Purdue Fort Wayne Mastodons": "Purdue Fort Wayne",
    "Purdue-Fort Wayne": "Purdue Fort Wayne",
    "IPFW": "Purdue Fort Wayne",
    "Fort Wayne": "Purdue Fort Wayne",
    "PFW": "Purdue Fort Wayne",

    "UC-Davis": "UC Davis",
    "UC Davis Aggies": "UC Davis",

    "UC-Irvine": "UC Irvine",
    "UC Irvine Anteaters": "UC Irvine",

    "UC-Riverside": "UC Riverside",
    "UC Riverside Highlanders": "UC Riverside",

    "UC-San Diego": "UC San Diego",
    "UC San Diego Tritons": "UC San Diego",
    "UCSD": "UC San Diego",

    "UC-Santa Barbara": "UC Santa Barbara",
    "UC Santa Barbara Gauchos": "UC Santa Barbara",
    "UCSB": "UC Santa Barbara",

    "East. Kentucky": "Eastern Kentucky",
    "Eastern Kentucky Colonels": "Eastern Kentucky",
    "EKU": "Eastern Kentucky",
    "E Kentucky": "Eastern Kentucky",
    "E. Kentucky": "Eastern Kentucky",

    "East. Michigan": "Eastern Michigan",
    "Eastern Michigan Eagles": "Eastern Michigan",
    "EMU": "Eastern Michigan",
    "E Michigan": "Eastern Michigan",
    "E. Michigan": "Eastern Michigan",

    "East. Illinois": "Eastern Illinois",
    "Eastern Illinois Panthers": "Eastern Illinois",
    "EIU": "Eastern Illinois",
    "E Illinois": "Eastern Illinois",
    "E. Illinois": "Eastern Illinois",

    "East. Washington": "Eastern Washington",
    "Eastern Washington Eagles": "Eastern Washington",
    "EWU": "Eastern Washington",
    "E Washington": "Eastern Washington",
    "E. Washington": "Eastern Washington",

    "West. Kentucky": "Western Kentucky",
    "Western Kentucky Hilltoppers": "Western Kentucky",
    "WKU": "Western Kentucky",
    "W Kentucky": "Western Kentucky",
    "W. Kentucky": "Western Kentucky",

    "West. Michigan": "Western Michigan",
    "Western Michigan Broncos": "Western Michigan",
    "WMU": "Western Michigan",
    "W Michigan": "Western Michigan",
    "W. Michigan": "Western Michigan",

    "West. Illinois": "Western Illinois",
    "Western Illinois Leathernecks": "Western Illinois",
    "W Illinois": "Western Illinois",
    "W. Illinois": "Western Illinois",

    "West. Carolina": "Western Carolina",
    "Western Carolina Catamounts": "Western Carolina",
    "W Carolina": "Western Carolina",
    "W. Carolina": "Western Carolina",

    "Northern Iowa Panthers": "Northern Iowa",
    "UNI": "Northern Iowa",
    "N Iowa": "Northern Iowa",
    "N. Iowa": "Northern Iowa",

    "Northern Kentucky Norse": "Northern Kentucky",
    "NKU": "Northern Kentucky",
    "N Kentucky": "Northern Kentucky",
    "N. Kentucky": "Northern Kentucky",

    "Northern Illinois Huskies": "Northern Illinois",
    "NIU": "Northern Illinois",
    "N Illinois": "Northern Illinois",
    "N. Illinois": "Northern Illinois",

    "Northern Arizona Lumberjacks": "Northern Arizona",
    "NAU": "Northern Arizona",
    "N Arizona": "Northern Arizona",
    "N. Arizona": "Northern Arizona",

    "Northern Colorado Bears": "Northern Colorado",
    "N Colorado": "Northern Colorado",
    "N. Colorado": "Northern Colorado",

    "Central Michigan Chippewas": "Central Michigan",
    "C Michigan": "Central Michigan",
    "C. Michigan": "Central Michigan",
    "CMU": "Central Michigan",

    "Central Arkansas Bears": "Central Arkansas",
    "C Arkansas": "Central Arkansas",

    "William and Mary": "William & Mary",
    "William and Mary Tribe": "William & Mary",
    "William & Mary Tribe": "William & Mary",
    "W&M": "William & Mary",

    "Southern Illinois Salukis": "Southern Illinois",
    "SIU": "Southern Illinois",
    "S Illinois": "Southern Illinois",
    "S. Illinois": "Southern Illinois",

    "South Alabama Jaguars": "South Alabama",
    "S Alabama": "South Alabama",
    "S. Alabama": "South Alabama",
    "USA": "South Alabama",

    "Middle Tennessee State": "Middle Tennessee",
    "Middle Tennessee St.": "Middle Tennessee",
    "Middle Tenn": "Middle Tennessee",
    "Middle Tenn.": "Middle Tennessee",
    "MTSU": "Middle Tennessee",
    "Middle Tennessee Blue Raiders": "Middle Tennessee",

    "Florida Atlantic Owls": "Florida Atlantic",
    "FAU": "Florida Atlantic",
    "Fla Atlantic": "Florida Atlantic",

    "Florida Gulf Coast Eagles": "Florida Gulf Coast",
    "FGCU": "Florida Gulf Coast",
    "Fla Gulf Coast": "Florida Gulf Coast",

    "Florida A&M Rattlers": "Florida A&M",
    "FAMU": "Florida A&M",

    "Southern Utah Thunderbirds": "Southern Utah",
    "SUU": "Southern Utah",

    "Utah Valley Wolverines": "Utah Valley",
    "UVU": "Utah Valley",

    "Utah Tech Trailblazers": "Utah Tech",
    "Dixie State": "Utah Tech",
    "Dixie St.": "Utah Tech",

    "Grand Canyon Antelopes": "Grand Canyon",
    "GCU": "Grand Canyon",

    "George Mason Patriots": "George Mason",
    "GMU": "George Mason",

    "George Washington Colonials": "George Washington",
    "GW": "George Washington",
    "GWU": "George Washington",

    "Georgia Tech Yellow Jackets": "Georgia Tech",
    "Ga Tech": "Georgia Tech",
    "GT": "Georgia Tech",

    "Gardner-Webb": "Gardner Webb",
    "Gardner Webb Runnin' Bulldogs": "Gardner Webb",

    "Bethune-Cookman": "Bethune Cookman",
    "Bethune Cookman Wildcats": "Bethune Cookman",
    "B-CU": "Bethune Cookman",

    "Fairleigh Dickinson Knights": "Fairleigh Dickinson",
    "FDU": "Fairleigh Dickinson",

    "Little Rock Trojans": "Little Rock",
    "Arkansas-Little Rock": "Little Rock",
    "UALR": "Little Rock",
    "Arkansas Little Rock": "Little Rock",

    "North Alabama Lions": "North Alabama",
    "UNA": "North Alabama",

    "Louisiana Ragin' Cajuns": "Louisiana",
    "Louisiana-Lafayette": "Louisiana",
    "Louisiana Lafayette": "Louisiana",
    "UL Lafayette": "Louisiana",
    "ULL": "Louisiana",

    "Louisiana-Monroe": "Louisiana Monroe",
    "Louisiana Monroe Warhawks": "Louisiana Monroe",
    "ULM": "Louisiana Monroe",
    "UL Monroe": "Louisiana Monroe",

    "Louisiana Tech Bulldogs": "Louisiana Tech",
    "La Tech": "Louisiana Tech",
    "LA Tech": "Louisiana Tech",

    "Detroit Mercy Titans": "Detroit Mercy",
    "Detroit": "Detroit Mercy",
    "U of D Mercy": "Detroit Mercy",
    "UDM": "Detroit Mercy",

    "Coastal Carolina Chanticleers": "Coastal Carolina",
    "CCU": "Coastal Carolina",

    "Green Bay Phoenix": "Green Bay",
    "Wisconsin-Green Bay": "Green Bay",
    "UW-Green Bay": "Green Bay",
    "UWGB": "Green Bay",

    "Milwaukee Panthers": "Milwaukee",
    "Wisconsin-Milwaukee": "Milwaukee",
    "UW-Milwaukee": "Milwaukee",
    "UWM": "Milwaukee",

    "Oral Roberts Golden Eagles": "Oral Roberts",
    "ORU": "Oral Roberts",

    "VMI Keydets": "VMI",
    "Virginia Military": "VMI",
    "Virginia Military Institute": "VMI",

    "West Georgia Wolves": "West Georgia",
    "W Georgia": "West Georgia",
    "W. Georgia": "West Georgia",
    "UWG": "West Georgia",

    "Southern Indiana Screaming Eagles": "Southern Indiana",
    "USI": "Southern Indiana",
    "S Indiana": "Southern Indiana",

    "Stonehill Skyhawks": "Stonehill",

    "Le Moyne Dolphins": "Le Moyne",
    "LeMoyne": "Le Moyne",

    "Mercyhurst Lakers": "Mercyhurst",

    "Lindenwood Lions": "Lindenwood",

    "Queens Royals": "Queens",
    "Queens (NC)": "Queens",

    "Duke Blue Devils": "Duke",
    "Kansas Jayhawks": "Kansas",
    "Kentucky Wildcats": "Kentucky",
    "Auburn Tigers": "Auburn",
    "Houston Cougars": "Houston",
    "Purdue Boilermakers": "Purdue",
    "Tennessee Volunteers": "Tennessee",
    "Alabama Crimson Tide": "Alabama",
    "Florida Gators": "Florida",
    "Gonzaga Bulldogs": "Gonzaga",
    "Michigan Wolverines": "Michigan",
    "Illinois Fighting Illini": "Illinois",
    "Indiana Hoosiers": "Indiana",
    "Texas Longhorns": "Texas",
    "Wisconsin Badgers": "Wisconsin",
    "Marquette Golden Eagles": "Marquette",
    "Creighton Bluejays": "Creighton",
    "Villanova Wildcats": "Villanova",
    "Xavier Musketeers": "Xavier",
    "Georgetown Hoyas": "Georgetown",
    "Seton Hall Pirates": "Seton Hall",
    "Providence Friars": "Providence",
    "Butler Bulldogs": "Butler",
    "Dayton Flyers": "Dayton",
    "Cincinnati Bearcats": "Cincinnati",
    "Memphis Tigers": "Memphis",
    "Louisville Cardinals": "Louisville",
    "Virginia Cavaliers": "Virginia",
    "Virginia Tech Hokies": "Virginia Tech",
    "Wake Forest Demon Deacons": "Wake Forest",
    "Syracuse Orange": "Syracuse",
    "Clemson Tigers": "Clemson",
    "Notre Dame Fighting Irish": "Notre Dame",
    "Stanford Cardinal": "Stanford",
    "California Golden Bears": "California",
    "Colorado Buffaloes": "Colorado",
    "Oklahoma Sooners": "Oklahoma",
    "Baylor Bears": "Baylor",
    "Texas Tech Red Raiders": "Texas Tech",
    "UCLA Bruins": "UCLA",
    "Iowa Hawkeyes": "Iowa",
    "Minnesota Golden Gophers": "Minnesota",
    "Rutgers Scarlet Knights": "Rutgers",
    "Nebraska Cornhuskers": "Nebraska",
    "Northwestern Wildcats": "Northwestern",
    "Maryland Terrapins": "Maryland",
    "Georgia Bulldogs": "Georgia",
    "Missouri Tigers": "Missouri",
    "Arkansas Razorbacks": "Arkansas",
    "South Carolina Gamecocks": "South Carolina",
    "Vanderbilt Commodores": "Vanderbilt",
    "Drake Bulldogs": "Drake",
    "Davidson Wildcats": "Davidson",
    "Richmond Spiders": "Richmond",
    "San Francisco Dons": "San Francisco",
    "Santa Clara Broncos": "Santa Clara",
    "Gonzaga Zags": "Gonzaga",
    "Belmont Bruins": "Belmont",
    "Furman Paladins": "Furman",
    "Samford Bulldogs": "Samford",
    "Colgate Raiders": "Colgate",
    "Yale Bulldogs": "Yale",
    "Princeton Tigers": "Princeton",
    "Vermont Catamounts": "Vermont",
    "Iona Gaels": "Iona",
    "Liberty Flames": "Liberty"
}
